aiohttphelper/__init__.py
aiohttphelper/functions.py
aiohttphelper-2.3.0.dist-info/LICENSE
aiohttphelper-2.3.0.dist-info/METADATA
aiohttphelper-2.3.0.dist-info/WHEEL
aiohttphelper-2.3.0.dist-info/top_level.txt
aiohttphelper-2.3.0.dist-info/RECORD
