Metadata-Version: 2.1
Name: aiohttphelper
Version: 2.3.0
Summary: Simple wrapper for aiohttp. Designed for my own use but might be useful to others.
Home-page: https://github.com/gregorybarille/aiocalls
Author: Gregory Barillé
Author-email: contact@gregorybarille.io
License: UNKNOWN
Platform: UNKNOWN
Classifier: Programming Language :: Python :: 3.6
Classifier: Programming Language :: Python :: 3.7
Classifier: Programming Language :: Python :: 3.8
Classifier: Programming Language :: Python :: 3.9
Classifier: License :: OSI Approved :: MIT License
Classifier: Operating System :: OS Independent
Requires-Python: >=3.6
Requires-Dist: aiohttp[speedups] (==3.6.2)
